buildmcp/__init__.py
buildmcp/__main__.py
buildmcp/builder.py
buildmcp/checksum.py
buildmcp-0.2.1.dist-info/METADATA
buildmcp-0.2.1.dist-info/WHEEL
buildmcp-0.2.1.dist-info/entry_points.txt
buildmcp-0.2.1.dist-info/licenses/LICENSE
buildmcp-0.2.1.dist-info/RECORD
