Metadata-Version: 2.4
Name: buildmcp
Version: 0.2.1
Summary: Build and deploy MCP server configurations from templates
Project-URL: Homepage, https://github.com/starbased-co/buildmcp
Project-URL: Repository, https://github.com/starbased-co/buildmcp
Project-URL: Issues, https://github.com/starbased-co/buildmcp/issues
Author-email: starbased <s@starbased.net>
License: MIT
License-File: LICENSE
Keywords: cli,configuration,mcp,template
Classifier: Development Status :: 3 - Alpha
Classifier: Intended Audience :: Developers
Classifier: License :: OSI Approved :: MIT License
Classifier: Programming Language :: Python :: 3
Classifier: Programming Language :: Python :: 3.12
Requires-Python: >=3.12
Requires-Dist: attrs
Requires-Dist: dpath>=2.2.0
Requires-Dist: pyjson5>=2.0.0
Requires-Dist: rich
Requires-Dist: tyro
